imgproc/__init__.py
imgproc/cpp/Binarization.cpp
imgproc/cpp/Binarization.hpp
imgproc/cpp/LineSegmentation.cpp
imgproc/cpp/LineSegmentation.hpp
imgproc/cpp/Scanner.cpp
imgproc/cpp/Scanner.hpp
imgproc/cpp/main.cpp
text_segmt-0.1.0.data/data/preprocess_images.py
text_segmt-0.1.0.dist-info/METADATA
text_segmt-0.1.0.dist-info/WHEEL
text_segmt-0.1.0.dist-info/top_level.txt
text_segmt-0.1.0.dist-info/RECORD
